setup.py
jz/__init__.py
jz.filerepresentation.egg-info/PKG-INFO
jz.filerepresentation.egg-info/SOURCES.txt
jz.filerepresentation.egg-info/dependency_links.txt
jz.filerepresentation.egg-info/namespace_packages.txt
jz.filerepresentation.egg-info/requires.txt
jz.filerepresentation.egg-info/top_level.txt
jz/filerepresentation/__init__.py
jz/filerepresentation/configure.zcml
jz/filerepresentation/filename.py
jz/filerepresentation/interfaces.py
jz/filerepresentation/jz.filerepresentation-configure.zcml
jz/filerepresentation/readme.txt
jz/filerepresentation/tests/__init__.py
jz/filerepresentation/tests/test_filename.py
