Metadata-Version: 1.0
Name: jz.filerepresentation
Version: 0.1
Summary: File representation components (zope).
Home-page: http://www.jellofishi.com/zope
Author: Gabi Shaar
Author-email: gabi@jbox-comp.com
License: GPL
Platform: UNKNOWN
